httpchunked.py
httpchunked-0.1.2.dist-info/LICENSE
httpchunked-0.1.2.dist-info/METADATA
httpchunked-0.1.2.dist-info/WHEEL
httpchunked-0.1.2.dist-info/top_level.txt
httpchunked-0.1.2.dist-info/RECORD
