Metadata-Version: 2.1
Name: httpchunked
Version: 0.1.2
Summary: Chunked transfer encoding as defined in RFC 7230
Home-page: https://github.com/jdeflander/httpchunked
Author: Jasper Deflander
License: MIT
Platform: UNKNOWN
Classifier: License :: OSI Approved :: MIT License
Classifier: Operating System :: OS Independent
Classifier: Programming Language :: Python :: 3.5
Requires-Python: >=3.5
